checkmate/__init__.py
checkmate/_version.py
checkmate/checkmate.tcss
checkmate/config.py
checkmate/exceptions.py
checkmate/main.py
checkmate/models.py
checkmate/repository.py
checkmate/services.py
checkmate/screens/__init__.py
checkmate/screens/confirm.py
checkmate/screens/create_task.py
checkmate/screens/filter.py
checkmate/screens/sort_select.py
checkmate/screens/todo_list.py
checkmate/widgets/__init__.py
checkmate/widgets/task_list.py
trly_checkmate-0.1.6.dist-info/METADATA
trly_checkmate-0.1.6.dist-info/WHEEL
trly_checkmate-0.1.6.dist-info/entry_points.txt
trly_checkmate-0.1.6.dist-info/top_level.txt
trly_checkmate-0.1.6.dist-info/RECORD
